python2_secrets-1.0.4.dist-info/METADATA
python2_secrets-1.0.4.dist-info/RECORD
python2_secrets-1.0.4.dist-info/WHEEL
python2_secrets-1.0.4.dist-info/top_level.txt
secrets/__init__.py
secrets/secrets.py
